bs4_web_scraper/__init__.py
bs4_web_scraper/base.py
bs4_web_scraper/exceptions.py
bs4_web_scraper/file_handler.py
bs4_web_scraper/logger.py
bs4_web_scraper/request_limiter.py
bs4_web_scraper/scraper.py
bs4_web_scraper/translate.py
bs4_web_scraper/utils.py
bs4_web_scraper-0.2.2.dist-info/LICENSE.md
bs4_web_scraper-0.2.2.dist-info/METADATA
bs4_web_scraper-0.2.2.dist-info/WHEEL
bs4_web_scraper-0.2.2.dist-info/top_level.txt
bs4_web_scraper-0.2.2.dist-info/RECORD
