Metadata-Version: 2.1
Name: bs4-web-scraper
Version: 0.2.2
Summary: A web scraper based on the BeautifulSoup4 library and translators package.
Author-email: ti-oluwa <tioluwa.dev@gmail.com>
Maintainer-email: ti-oluwa <tioluwa.dev@gmail.com>
Project-URL: Homepage, https://github.com/ti-oluwa/bs4_web_scraper
Project-URL: Bug Tracker, https://github.com/ti-oluwa/bs4_web_scraper/issues
Project-URL: Repository, https://github.com/ti-oluwa/bs4_web_scraper
Keywords: web scraper,bs4,beautifulsoup4,web scraping,web scraping with python,web scraping with bs4,web scraping with beautifulsoup4,web scraping with translation,web scraping with translation to other languages,web scraping with translation to other languages with python,web scraping with translation to other languages with bs4,web scraping with translation to other languages with beautifulsoup4,web scraping with translation to other languages with python and bs4,web scraping with translation 
Classifier: Programming Language :: Python :: 3
Classifier: License :: OSI Approved :: MIT License
Classifier: Operating System :: OS Independent
Classifier: Development Status :: 5 - Production/Stable
Classifier: Environment :: Console
Requires-Python: >=3.7
License-File: LICENSE.md
Requires-Dist: beautifulsoup4 >=4.11.2
Requires-Dist: lxml >=4.9.2
Requires-Dist: requests >=2.28.1
Requires-Dist: html5lib >=1.1
Requires-Dist: urllib3 >=1.26.13
Requires-Dist: pytz >=2022.7.1
Requires-Dist: translators >=5.5.6
Requires-Dist: toml
Requires-Dist: pyyaml
